qsymm/__init__.py
qsymm/_static_version.py
qsymm/_version.py
qsymm/groups.py
qsymm/hamiltonian_generator.py
qsymm/kwant_continuum.py
qsymm/kwant_linalg_lll.py
qsymm/kwant_rmt.py
qsymm/linalg.py
qsymm/model.py
qsymm/symmetry_finder.py
qsymm/tests/__init__.py
qsymm/tests/test_groups.py
qsymm/tests/test_hamiltonian_generator.py
qsymm/tests/test_model.py
qsymm/tests/test_mutual.py
qsymm/tests/test_symmetry_finder.py
qsymm/tests/test_util.py
qsymm-1.4.0.dist-info/AUTHORS.md
qsymm-1.4.0.dist-info/LICENSE
qsymm-1.4.0.dist-info/METADATA
qsymm-1.4.0.dist-info/WHEEL
qsymm-1.4.0.dist-info/top_level.txt
qsymm-1.4.0.dist-info/RECORD
