Metadata-Version: 2.1
Name: qsymm
Version: 1.4.0
Summary: Symmetry finder and symmetric Hamiltonian generator
Home-page: https://gitlab.kwant-project.org/qt/qsymm
Author: Qsymm authors
License: BSD
Classifier: Development Status :: 4 - Beta
Classifier: License :: OSI Approved :: BSD License
Classifier: Intended Audience :: Science/Research
Classifier: Programming Language :: Python :: 3.7
Requires-Python: >=3.7
License-File: LICENSE
License-File: AUTHORS.md
Requires-Dist: numpy >=1.16.2
Requires-Dist: scipy >=1.1
Requires-Dist: sympy >=1.3.0
Requires-Dist: tinyarray >=1.2.2
Provides-Extra: kwant
Requires-Dist: kwant ; extra == 'kwant'
